Apagar/__init__.py
Apagar/__main__.py
Apagar-0.0.4.dist-info/LICENSE
Apagar-0.0.4.dist-info/METADATA
Apagar-0.0.4.dist-info/WHEEL
Apagar-0.0.4.dist-info/top_level.txt
Apagar-0.0.4.dist-info/RECORD
