Metadata-Version: 2.1
Name: Apagar
Version: 0.0.4
Summary: Simple Hello World
Home-page: 
Author: Claudio Torres Arbe
Author-email: claudiotarbe@gmail.com
Classifier: Programming Language :: Python :: 3.8
Classifier: License :: OSI Approved :: MIT License
Classifier: Operating System :: OS Independent
Requires-Python: >=3.6
License-File: LICENSE
